{
  "generatedAt": "2026-07-21T14:19:23.441642+00:00",
  "sourceStatus": {
    "usgs": "live where gage IDs are mapped",
    "nws": "live point/hourly forecasts",
    "reports": "manual placeholders"
  },
  "quality": {
    "successfulForecasts": 12,
    "successfulUsgs": 10,
    "totalReaches": 12
  },
  "reaches": [
    {
      "id": "boise-main-town",
      "forecast": [
        {
          "label": "Morning",
          "temp": "77F",
          "wind": "1 mph",
          "note": "areas of smoke"
        },
        {
          "label": "Midday",
          "temp": "88F",
          "wind": "5 mph",
          "note": "patchy smoke"
        },
        {
          "label": "Afternoon",
          "temp": "98F",
          "wind": "9 mph",
          "note": "patchy smoke"
        },
        {
          "label": "Evening",
          "temp": "96F",
          "wind": "10 mph",
          "note": "patchy smoke"
        }
      ],
      "sourceErrors": [],
      "flow": "639 cfs",
      "flowSourceSite": "13206000",
      "flowCfs": 639,
      "gageHeight": "4.06 ft",
      "gageHeightSourceSite": "13206000",
      "gageHeightFt": 4.06,
      "status": "watch",
      "score": 75,
      "pressure": "forecast-driven",
      "weather": "areas of smoke",
      "why": "Condition score uses reach-specific flow range, trout temperature, weather, and gage confidence; flow is in this reach's ideal range (300-900 cfs), water temperature is missing, so temperature confidence is limited, forecast window is available, wind data is available, gage confidence is moderate."
    },
    {
      "id": "boise-south-fork",
      "forecast": [
        {
          "label": "Morning",
          "temp": "77F",
          "wind": "3 mph",
          "note": "slight chance rain showers"
        },
        {
          "label": "Midday",
          "temp": "92F",
          "wind": "7 mph",
          "note": "patchy smoke"
        },
        {
          "label": "Afternoon",
          "temp": "97F",
          "wind": "12 mph",
          "note": "mostly sunny"
        },
        {
          "label": "Evening",
          "temp": "90F",
          "wind": "13 mph",
          "note": "patchy smoke"
        }
      ],
      "sourceErrors": [],
      "flow": "1,570 cfs",
      "flowSourceSite": "13190500",
      "flowCfs": 1570,
      "gageHeight": "4.89 ft",
      "gageHeightSourceSite": "13190500",
      "gageHeightFt": 4.89,
      "water": "48F",
      "waterTempSourceSite": "13190500",
      "waterTempF": 47.7,
      "status": "watch",
      "score": 80,
      "pressure": "forecast-driven",
      "weather": "slight chance rain showers",
      "why": "Condition score uses reach-specific flow range, trout temperature, weather, and gage confidence; flow is in this reach's ideal range (600-1,600 cfs), water temperature is productive for trout, forecast window is available, wind data is available, storm or precipitation risk lowers confidence, gage confidence is moderate."
    },
    {
      "id": "boise-middle-fork",
      "forecast": [
        {
          "label": "Morning",
          "temp": "70F",
          "wind": "3 mph",
          "note": "chance rain showers"
        },
        {
          "label": "Midday",
          "temp": "87F",
          "wind": "3 mph",
          "note": "slight chance rain showers"
        },
        {
          "label": "Afternoon",
          "temp": "90F",
          "wind": "7 mph",
          "note": "chance showers and thunderstorms"
        },
        {
          "label": "Evening",
          "temp": "82F",
          "wind": "7 mph",
          "note": "patchy smoke"
        }
      ],
      "sourceErrors": [],
      "flow": "484 cfs",
      "flowSourceSite": "13185000",
      "flowCfs": 484,
      "gageHeight": "5.66 ft",
      "gageHeightSourceSite": "13185000",
      "gageHeightFt": 5.66,
      "status": "watch",
      "score": 70,
      "pressure": "forecast-driven",
      "weather": "chance rain showers",
      "why": "Condition score uses reach-specific flow range, trout temperature, weather, and gage confidence; flow is in this reach's ideal range (250-900 cfs), water temperature is missing, so temperature confidence is limited, forecast window is available, wind data is available, storm or precipitation risk lowers confidence, gage confidence is moderate."
    },
    {
      "id": "henrys-fork-box",
      "forecast": [
        {
          "label": "Morning",
          "temp": "67F",
          "wind": "5 mph",
          "note": "slight chance light rain"
        },
        {
          "label": "Midday",
          "temp": "82F",
          "wind": "2 mph",
          "note": "slight chance light rain"
        },
        {
          "label": "Afternoon",
          "temp": "84F",
          "wind": "5 mph",
          "note": "slight chance showers and thunderstorms"
        },
        {
          "label": "Evening",
          "temp": "74F",
          "wind": "6 mph",
          "note": "partly cloudy"
        }
      ],
      "sourceErrors": [],
      "flow": "1,470 cfs",
      "flowSourceSite": "13042500",
      "flowCfs": 1470,
      "gageHeight": "4.66 ft",
      "gageHeightSourceSite": "13042500",
      "gageHeightFt": 4.66,
      "status": "limited",
      "score": 61,
      "pressure": "forecast-driven",
      "weather": "slight chance light rain",
      "why": "Condition score uses reach-specific flow range, trout temperature, weather, and gage confidence; flow is usable but above the ideal range (700-1,400 cfs), water temperature is missing, so temperature confidence is limited, forecast window is available, wind data is available, storm or precipitation risk lowers confidence, gage confidence is moderate."
    },
    {
      "id": "henrys-fork-ranch",
      "forecast": [
        {
          "label": "Morning",
          "temp": "69F",
          "wind": "5 mph",
          "note": "slight chance light rain"
        },
        {
          "label": "Midday",
          "temp": "83F",
          "wind": "3 mph",
          "note": "slight chance light rain"
        },
        {
          "label": "Afternoon",
          "temp": "86F",
          "wind": "6 mph",
          "note": "slight chance showers and thunderstorms"
        },
        {
          "label": "Evening",
          "temp": "74F",
          "wind": "8 mph",
          "note": "slight chance showers and thunderstorms"
        }
      ],
      "sourceErrors": [],
      "flow": "1,470 cfs",
      "flowSourceSite": "13042500",
      "flowCfs": 1470,
      "gageHeight": "4.66 ft",
      "gageHeightSourceSite": "13042500",
      "gageHeightFt": 4.66,
      "status": "limited",
      "score": 61,
      "pressure": "forecast-driven",
      "weather": "slight chance light rain",
      "why": "Condition score uses reach-specific flow range, trout temperature, weather, and gage confidence; flow is usable but above the ideal range (600-1,200 cfs), water temperature is missing, so temperature confidence is limited, forecast window is available, wind data is available, storm or precipitation risk lowers confidence, gage confidence is moderate."
    },
    {
      "id": "snake-south-fork-canyon",
      "forecast": [
        {
          "label": "Morning",
          "temp": "69F",
          "wind": "7 mph",
          "note": "slight chance light rain"
        },
        {
          "label": "Midday",
          "temp": "88F",
          "wind": "3 mph",
          "note": "slight chance light rain"
        },
        {
          "label": "Afternoon",
          "temp": "91F",
          "wind": "5 mph",
          "note": "chance showers and thunderstorms"
        },
        {
          "label": "Evening",
          "temp": "81F",
          "wind": "3 mph",
          "note": "chance showers and thunderstorms"
        }
      ],
      "sourceErrors": [],
      "flow": "13,500 cfs",
      "flowSourceSite": "13032500",
      "flowCfs": 13500,
      "gageHeight": "9.16 ft",
      "gageHeightSourceSite": "13032500",
      "gageHeightFt": 9.16,
      "status": "watch",
      "score": 70,
      "pressure": "forecast-driven",
      "weather": "slight chance light rain",
      "why": "Condition score uses reach-specific flow range, trout temperature, weather, and gage confidence; flow is in this reach's ideal range (8,000-14,000 cfs), water temperature is missing, so temperature confidence is limited, forecast window is available, wind data is available, storm or precipitation risk lowers confidence, gage confidence is moderate."
    },
    {
      "id": "big-wood-ketchum",
      "forecast": [
        {
          "label": "Morning",
          "temp": "70F",
          "wind": "6 mph",
          "note": "slight chance light rain"
        },
        {
          "label": "Midday",
          "temp": "85F",
          "wind": "3 mph",
          "note": "slight chance light rain"
        },
        {
          "label": "Afternoon",
          "temp": "88F",
          "wind": "5 mph",
          "note": "slight chance showers and thunderstorms"
        },
        {
          "label": "Evening",
          "temp": "80F",
          "wind": "5 mph",
          "note": "slight chance showers and thunderstorms"
        }
      ],
      "sourceErrors": [],
      "flow": "238 cfs",
      "flowSourceSite": "13139510",
      "flowCfs": 238,
      "gageHeight": "1.87 ft",
      "gageHeightSourceSite": "13139510",
      "gageHeightFt": 1.87,
      "status": "watch",
      "score": 70,
      "pressure": "forecast-driven",
      "weather": "slight chance light rain",
      "why": "Condition score uses reach-specific flow range, trout temperature, weather, and gage confidence; flow is in this reach's ideal range (150-500 cfs), water temperature is missing, so temperature confidence is limited, forecast window is available, wind data is available, storm or precipitation risk lowers confidence, gage confidence is moderate."
    },
    {
      "id": "silver-creek-preserve",
      "forecast": [
        {
          "label": "Morning",
          "temp": "73F",
          "wind": "3 mph",
          "note": "partly sunny"
        },
        {
          "label": "Midday",
          "temp": "88F",
          "wind": "3 mph",
          "note": "mostly sunny"
        },
        {
          "label": "Afternoon",
          "temp": "92F",
          "wind": "8 mph",
          "note": "slight chance showers and thunderstorms"
        },
        {
          "label": "Evening",
          "temp": "84F",
          "wind": "8 mph",
          "note": "slight chance showers and thunderstorms"
        }
      ],
      "sourceErrors": [],
      "flow": "109 cfs",
      "flowSourceSite": "13150430",
      "flowCfs": 109,
      "gageHeight": "6.76 ft",
      "gageHeightSourceSite": "13150430",
      "gageHeightFt": 6.76,
      "water": "66F",
      "waterTempSourceSite": "13150430",
      "waterTempF": 66.4,
      "status": "watch",
      "score": 68,
      "pressure": "forecast-driven",
      "weather": "partly sunny",
      "why": "Condition score uses reach-specific flow range, trout temperature, weather, and gage confidence; flow is in this reach's ideal range (80-180 cfs), water is warm; fish early and monitor stress, forecast window is available, wind data is available, storm or precipitation risk lowers confidence, gage confidence is moderate."
    },
    {
      "id": "teton-drictor",
      "forecast": [
        {
          "label": "Morning",
          "temp": "74F",
          "wind": "5 mph",
          "note": "slight chance light rain"
        },
        {
          "label": "Midday",
          "temp": "88F",
          "wind": "2 mph",
          "note": "slight chance light rain"
        },
        {
          "label": "Afternoon",
          "temp": "88F",
          "wind": "6 mph",
          "note": "chance showers and thunderstorms"
        },
        {
          "label": "Evening",
          "temp": "76F",
          "wind": "5 mph",
          "note": "slight chance showers and thunderstorms"
        }
      ],
      "sourceErrors": [],
      "flow": "305 cfs",
      "flowSourceSite": "13052200",
      "flowCfs": 305,
      "gageHeight": "2.04 ft",
      "gageHeightSourceSite": "13052200",
      "gageHeightFt": 2.04,
      "status": "watch",
      "score": 70,
      "pressure": "forecast-driven",
      "weather": "slight chance light rain",
      "why": "Condition score uses reach-specific flow range, trout temperature, weather, and gage confidence; flow is in this reach's ideal range (300-900 cfs), water temperature is missing, so temperature confidence is limited, forecast window is available, wind data is available, storm or precipitation risk lowers confidence, gage confidence is moderate."
    },
    {
      "id": "salmon-upper-stanley",
      "forecast": [
        {
          "label": "Morning",
          "temp": "57F",
          "wind": "0 mph",
          "note": "slight chance light rain"
        },
        {
          "label": "Midday",
          "temp": "77F",
          "wind": "2 mph",
          "note": "slight chance light rain"
        },
        {
          "label": "Afternoon",
          "temp": "83F",
          "wind": "3 mph",
          "note": "slight chance showers and thunderstorms"
        },
        {
          "label": "Evening",
          "temp": "77F",
          "wind": "3 mph",
          "note": "partly cloudy"
        }
      ],
      "sourceErrors": [],
      "status": "skip",
      "score": 39,
      "pressure": "forecast-driven",
      "weather": "slight chance light rain",
      "why": "Condition score uses reach-specific flow range, trout temperature, weather, and gage confidence; flow gage is not yet mapped or did not return live CFS, water temperature is missing, so temperature confidence is limited, forecast window is available, wind data is available, storm or precipitation risk lowers confidence, gage or flow-range confidence still needs local validation."
    },
    {
      "id": "clearwater-middle-fork",
      "forecast": [
        {
          "label": "Morning",
          "temp": "70F",
          "wind": "0 mph",
          "note": "patchy smoke"
        },
        {
          "label": "Midday",
          "temp": "90F",
          "wind": "1 mph",
          "note": "patchy smoke"
        },
        {
          "label": "Afternoon",
          "temp": "97F",
          "wind": "2 mph",
          "note": "patchy smoke"
        },
        {
          "label": "Evening",
          "temp": "87F",
          "wind": "1 mph",
          "note": "patchy smoke"
        }
      ],
      "sourceErrors": [],
      "status": "skip",
      "score": 44,
      "pressure": "forecast-driven",
      "weather": "patchy smoke",
      "why": "Condition score uses reach-specific flow range, trout temperature, weather, and gage confidence; flow gage is not yet mapped or did not return live CFS, water temperature is missing, so temperature confidence is limited, forecast window is available, wind data is available, gage or flow-range confidence still needs local validation."
    },
    {
      "id": "st-joe-upper",
      "forecast": [
        {
          "label": "Morning",
          "temp": "72F",
          "wind": "2 mph",
          "note": "haze"
        },
        {
          "label": "Midday",
          "temp": "86F",
          "wind": "1 mph",
          "note": "haze"
        },
        {
          "label": "Afternoon",
          "temp": "89F",
          "wind": "3 mph",
          "note": "haze"
        },
        {
          "label": "Evening",
          "temp": "81F",
          "wind": "2 mph",
          "note": "haze"
        }
      ],
      "sourceErrors": [],
      "flow": "701 cfs",
      "flowSourceSite": "12414500",
      "flowCfs": 701,
      "gageHeight": "6.00 ft",
      "gageHeightSourceSite": "12414500",
      "gageHeightFt": 6.0,
      "status": "watch",
      "score": 68,
      "pressure": "forecast-driven",
      "weather": "haze",
      "why": "Condition score uses reach-specific flow range, trout temperature, weather, and gage confidence; flow is usable but below the ideal range (800-3,000 cfs), water temperature is missing, so temperature confidence is limited, forecast window is available, wind data is available, gage confidence is moderate."
    }
  ]
}
